m2_kernel/__init__.py
m2_kernel/__main__.py
m2_kernel/install.py
m2_kernel/kernel.py
m2_kernel/assets/m2-code/init.m2
m2_kernel/assets/m2-code/test.txt
m2_kernel/assets/m2-mode/macaulay2.js
m2_kernel/assets/m2-mode/main.js
m2_kernel/assets/m2-spec/kernel.js
passagemath_macaulay2_jupyterkernel-0.6.7.2.data/data/share/jupyter/kernels/m2/kernel.js
passagemath_macaulay2_jupyterkernel-0.6.7.2.data/data/share/jupyter/kernels/m2/kernel.json
passagemath_macaulay2_jupyterkernel-0.6.7.2.dist-info/licenses/LICENSE
passagemath_macaulay2_jupyterkernel-0.6.7.2.dist-info/METADATA
passagemath_macaulay2_jupyterkernel-0.6.7.2.dist-info/WHEEL
passagemath_macaulay2_jupyterkernel-0.6.7.2.dist-info/top_level.txt
passagemath_macaulay2_jupyterkernel-0.6.7.2.dist-info/RECORD
