Metadata-Version: 2.4
Name: passagemath-macaulay2-jupyterkernel
Version: 0.6.7.2
Summary: Jupyter kernel for Macaulay2 (passagemath fork)
Author-email: Radoslav Zlatev <radoslav@math.cornell.edu>
Maintainer: Matthias Koeppe and passagemath contributors
Project-URL: Homepage, https://github.com/passagemath/passagemath-macaulay2-jupyterkernel
Classifier: Development Status :: 4 - Beta
Classifier: Programming Language :: Python :: 3.7
Classifier: Operating System :: MacOS :: MacOS X
Classifier: Operating System :: POSIX :: Linux
Classifier: License :: OSI Approved :: MIT License
License-File: LICENSE
Requires-Dist: ipykernel
Requires-Dist: pexpect
Requires-Dist: passagemath-macaulay2
Dynamic: license-file
